Metadata-Version: 1.0
Name: yassin-distributions
Version: 1.1
Summary: Gaussian and Binomial distributions
Home-page: UNKNOWN
Author: Yassin elsaman
Author-email: yassinelsaman025@gmail.com
License: UNKNOWN
Platform: UNKNOWN
